szetop_backend_code_gen_mcp/__init__.py
szetop_backend_code_gen_mcp/server.py
szetop_backend_code_gen_mcp/prompt/__init__.py
szetop_backend_code_gen_mcp/prompt/prompt.py
szetop_backend_code_gen_mcp/prompt/prompts/add_api_20250518.txt
szetop_backend_code_gen_mcp/prompt/prompts/add_api_20250618.txt
szetop_backend_code_gen_mcp/prompt/prompts/describe_image_prompt.txt
szetop_backend_code_gen_mcp/prompt/prompts/general_api_20250617.txt
szetop_backend_code_gen_mcp/prompt/prompts/list_api_20250518.txt
szetop_backend_code_gen_mcp/prompt/prompts/list_api_20250617.txt
szetop_backend_code_gen_mcp/prompt/prompts/template/list.txt
szetop_backend_code_gen_mcp/prompt/prompts/template/列表提示词模板.txt
szetop_backend_code_gen_mcp/prompt/prompts/template/新增编辑提示词模板.txt
szetop_backend_code_gen_mcp/prompt/prompts/template/详情提示词模板.txt
szetop_backend_code_gen_mcp/services/__init__.py
szetop_backend_code_gen_mcp/services/api.py
szetop_backend_code_gen_mcp/services/coder.py
szetop_backend_code_gen_mcp/trae/__init__.py
szetop_backend_code_gen_mcp/trae/cert_installer.py
szetop_backend_code_gen_mcp/trae/extract_java_stack.py
szetop_backend_code_gen_mcp/trae/git_user.py
szetop_backend_code_gen_mcp/trae/machine.py
szetop_backend_code_gen_mcp/trae/proxy_set.py
szetop_backend_code_gen_mcp/trae/trae_env.py
szetop_backend_code_gen_mcp/trae/cert/mitmproxy-ca-cert.pem
szetop_backend_code_gen_mcp/trae/ide_template/springboot2/project_rules.md
szetop_backend_code_gen_mcp/trae/ide_template/springboot3/project_rules.md
szetop_backend_code_gen_mcp/utils/__init__.py
szetop_backend_code_gen_mcp/utils/dify.py
szetop_backend_code_gen_mcp/utils/image.py
szetop_backend_code_gen_mcp/utils/ocr.py
szetop_backend_code_gen_mcp/utils/parse_java_entity.py
szetop_backend_code_gen_mcp/vision/__init__.py
szetop_backend_code_gen_mcp/vision/anthropic.py
szetop_backend_code_gen_mcp/vision/cloudflare.py
szetop_backend_code_gen_mcp/vision/openai.py
szetop_backend_code_gen_mcp/vision/qwen.py
szetop_backend_code_gen_mcp-0.0.4.dist-info/METADATA
szetop_backend_code_gen_mcp-0.0.4.dist-info/WHEEL
szetop_backend_code_gen_mcp-0.0.4.dist-info/entry_points.txt
szetop_backend_code_gen_mcp-0.0.4.dist-info/top_level.txt
szetop_backend_code_gen_mcp-0.0.4.dist-info/RECORD
